backlinks/__init__.py
backlinks/macro.py
backlinks/new-macro.py
TracBackLinksMacro-8.1.dist-info/METADATA
TracBackLinksMacro-8.1.dist-info/WHEEL
TracBackLinksMacro-8.1.dist-info/entry_points.txt
TracBackLinksMacro-8.1.dist-info/top_level.txt
TracBackLinksMacro-8.1.dist-info/RECORD
