Metadata-Version: 2.1
Name: TracBackLinksMacro
Version: 8.1
Summary: A wiki macro to show links to other wiki pages which link                      to the page the macro is called from.
Home-page: https://trac-hacks.org/wiki/BackLinksMacro
Author: Trapanator
Author-email: trap@trapanator.com
License: GPLv3
Platform: UNKNOWN
Requires-Dist: Trac
